xarpes/__init__.py
xarpes/bandmap.py
xarpes/constants.py
xarpes/distributions.py
xarpes/functions.py
xarpes/mdcs.py
xarpes/plotting.py
xarpes/selfenergies.py
xarpes/settings_parameters.py
xarpes/settings_plots.py
xarpes-0.6.3.dist-info/entry_points.txt
xarpes-0.6.3.dist-info/LICENSE
xarpes-0.6.3.dist-info/WHEEL
xarpes-0.6.3.dist-info/METADATA
xarpes-0.6.3.dist-info/RECORD
