Metadata-Version: 2.1
Name: xarpes
Version: 0.6.3
Summary: Extraction from angle resolved photoemission spectra
Author: xARPES Developers
Requires-Python: >=3.7.0
Classifier: License :: OSI Approved :: GNU General Public License v3 (GPLv3)
Classifier: Programming Language :: Python :: 3
Requires-Dist: igor2>=0.5.8
Requires-Dist: jupyterlab
Requires-Dist: jupytext
Requires-Dist: matplotlib<3.10.0
Requires-Dist: numpy
Requires-Dist: scipy
Requires-Dist: lmfit
Requires-Dist: pyqt5
Requires-Dist: ipympl>=0.9.3
Requires-Dist: ipywidgets>=8.1.5
Requires-Dist: ipykernel<6.32.0
Project-URL: Documentation, https://xarpes.github.io
